{"path": [{"lon": 11.5617, "lat": -4.889367, "pCode": "", "pName": "-4.8894,11.5617", "speed": 13, "gc": false, "locked": false, "waitHr": 0}, {"lon": 11.648465, "lat": -5.087758, "pCode": "", "pName": "", "speed": 13, "gc": false, "locked": false, "waitHr": 0}, {"lon": 11.735229, "lat": -5.286149, "pCode": "", "pName": "", "speed": 13, "gc": false, "locked": false, "waitHr": 0}, {"lon": 11.821994, "lat": -5.48454, "pCode": "", "pName": "", "speed": 13, "gc": false, "locked": false, "waitHr": 0}, {"lon": 11.908758, "lat": -5.682931, "pCode": "", "pName": "", "speed": 13, "gc": false, "locked": false, "waitHr": 0}, {"lon": 11.995523, "lat": -5.881323, "pCode": "", "pName": "", "speed": 13, "gc": false, "locked": false, "waitHr": 0}, {"lon": 12.082288, "lat": -6.079714, "pCode": "", "pName": "", "speed": 13, "gc": false, "locked": false, "waitHr": 0}, {"lon": 12.169052, "lat": -6.278105, "pCode": "", "pName": "", "speed": 13, "gc": false, "locked": false, "waitHr": 0}, {"lon": 12.255817, "lat": -6.476496, "pCode": "", "pName": "", "speed": 13, "gc": false, "locked": false, "waitHr": 0}, {"lon": 12.342582, "lat": -6.674887, "pCode": "", "pName": "", "speed": 13, "gc": false, "locked": false, "waitHr": 0}, {"lon": 12.429346, "lat": -6.873278, "pCode": "", "pName": "", "speed": 13, "gc": false, "locked": false, "waitHr": 0}, {"lon": 12.516111, "lat": -7.071669, "pCode": "", "pName": "", "speed": 13, "gc": false, "locked": false, "waitHr": 0}, {"lon": 12.602875, "lat": -7.27006, "pCode": "", "pName": "", "speed": 13, "gc": false, "locked": false, "waitHr": 0}, {"lon": 12.68964, "lat": -7.468451, "pCode": "", "pName": "", "speed": 13, "gc": false, "locked": false, "waitHr": 0}, {"lon": 12.776405, "lat": -7.666842, "pCode": "", "pName": "", "speed": 13, "gc": false, "locked": false, "waitHr": 0}, {"lon": 12.863169, "lat": -7.865234, "pCode": "", "pName": "", "speed": 13, "gc": false, "locked": false, "waitHr": 0}, {"lon": 12.949934, "lat": -8.063625, "pCode": "", "pName": "", "speed": 13, "gc": false, "locked": false, "waitHr": 0}, {"lon": 13.036699, "lat": -8.262016, "pCode": "", "pName": "", "speed": 13, "gc": false, "locked": false, "waitHr": 0}, {"lon": 13.123463, "lat": -8.460407, "pCode": "", "pName": "", "speed": 13, "gc": false, "locked": false, "waitHr": 0}, {"lon": 13.237067, "lat": -8.720167, "pCode": "", "pName": "-8.7202,13.2371", "speed": 13, "gc": false, "locked": false, "waitHr": 0}], "foundSol": true, "crushed": false, "errorMessage": ""}